cs/semantics.py
cs_semantics-20250103.dist-info/METADATA
cs_semantics-20250103.dist-info/WHEEL
cs_semantics-20250103.dist-info/top_level.txt
cs_semantics-20250103.dist-info/RECORD
